PyUploads/Exceptions.py
PyUploads/__init__.py
PyUploads-0.0.5.dist-info/METADATA
PyUploads-0.0.5.dist-info/WHEEL
PyUploads-0.0.5.dist-info/top_level.txt
PyUploads-0.0.5.dist-info/RECORD
