Metadata-Version: 2.1
Name: PyUploads
Version: 0.0.5
Summary: Wrapper for websites such as Throwbin.io
Home-page: https://github.com/Gowixx/PyUploads
Author: Gowixx
Author-email: <notgowixxmen@protonmail.ch>
License: UNKNOWN
Keywords: python,throwbin,pythrowbin,python throwbin,throwbin.io,python uploads,pyuploads
Platform: UNKNOWN
Requires-Dist: requests
